medutils/__init__.py
medutils/medutils.py
medutils-0.1.21.dist-info/LICENSE
medutils-0.1.21.dist-info/METADATA
medutils-0.1.21.dist-info/WHEEL
medutils-0.1.21.dist-info/top_level.txt
medutils-0.1.21.dist-info/RECORD
