Metadata-Version: 2.1
Name: medutils
Version: 0.1.21
Summary: A package of common utilities for medical images segmentation.
Home-page: https://github.com/Jingnan-Jia/medutils
Author: Jingnan
Author-email: jiajingnan2222@gmail.com
Classifier: Programming Language :: Python :: 3
Classifier: License :: OSI Approved :: MIT License
Classifier: Operating System :: OS Independent
Requires-Python: >=3.6
License-File: LICENSE
Requires-Dist: pingouin
